pointcloudset/pointcloud.py
pointcloudset/io/pointcloud/csv.py
pointcloudset/io/pointcloud/__init__.py
pointcloudset/io/pointcloud/pyntcloud.py
pointcloudset/io/pointcloud/las.py
pointcloudset/io/pointcloud/open3d.py
pointcloudset/io/pointcloud/pandas.py
pointcloudset/io/__init__.py
pointcloudset/io/dataset/dir.py
pointcloudset/io/dataset/pointcloud.py
pointcloudset/io/dataset/__init__.py
pointcloudset/io/dataset/ros.py
pointcloudset/io/dataset/commandline.py
pointcloudset/config.py
pointcloudset/__init__.py
pointcloudset/plot/pointcloud.py
pointcloudset/plot/__init__.py
pointcloudset/plot/dataset.py
pointcloudset/geometry/point.py
pointcloudset/geometry/__init__.py
pointcloudset/geometry/plane.py
pointcloudset/pointcloud_core.py
pointcloudset/dataset.py
pointcloudset/dataset_core.py
pointcloudset/filter/__init__.py
pointcloudset/filter/stat.py
pointcloudset/diff/nearest.py
pointcloudset/diff/point.py
pointcloudset/diff/pointcloud.py
pointcloudset/diff/__init__.py
pointcloudset/diff/origin.py
pointcloudset/diff/plane.py
pointcloudset/pipeline/__init__.py
pointcloudset/pipeline/delayed_result.py
pointcloudset-0.11.0.dist-info/WHEEL
pointcloudset-0.11.0.dist-info/entry_points.txt
pointcloudset-0.11.0.dist-info/METADATA
pointcloudset-0.11.0.dist-info/RECORD
