Metadata-Version: 2.3
Name: pointcloudset
Version: 0.11.0
Summary: Analyze large datasets of point clouds recorded over time in an efficient way
Author: VIRTUAL VEHICLE Research GmbH
Author-email: VIRTUAL VEHICLE Research GmbH <thomas.goelles@v2c2.at>
Classifier: Programming Language :: Python :: 3
Classifier: Programming Language :: Python :: 3.10
Classifier: Programming Language :: Python :: 3.11
Classifier: License :: OSI Approved :: MIT License
Classifier: Operating System :: POSIX :: Linux
Classifier: Intended Audience :: Developers
Classifier: Intended Audience :: Education
Classifier: Intended Audience :: Other Audience
Classifier: Intended Audience :: Science/Research
Classifier: Development Status :: 4 - Beta
Classifier: Natural Language :: English
Classifier: Topic :: Scientific/Engineering
Classifier: Topic :: Scientific/Engineering :: GIS
Classifier: Topic :: Scientific/Engineering :: Visualization
Classifier: Topic :: Scientific/Engineering :: Information Analysis
Classifier: Topic :: Utilities
Classifier: Typing :: Typed
Requires-Dist: numpy<2
Requires-Dist: pandas
Requires-Dist: pyntcloud
Requires-Dist: open3d>=0.16.0,<0.19.0
Requires-Dist: plotly
Requires-Dist: dask>=2023.11.0
Requires-Dist: typer
Requires-Dist: rich
Requires-Dist: rosbags>=0.9.15,<0.10.0
Requires-Dist: ipywidgets
Requires-Dist: laspy
Requires-Dist: pyarrow>=19.0.1
Requires-Python: >=3.10, <3.12
Project-URL: Bug Tracker, https://github.com/virtual-vehicle/pointcloudset/issues
Project-URL: Documentation, https://virtual-vehicle.github.io/pointcloudset/
Project-URL: Source, https://github.com/virtual-vehicle/pointcloudset
